insider/__init__.py
insider/apps.py
insider/db_router.py
insider/dispatch.py
insider/middleware.py
insider/models.py
insider/notifiers.py
insider/publishers.py
insider/registry.py
insider/settings.py
insider/tasks.py
insider/urls.py
insider/utils.py
insider/views.py
insider/api/__init__.py
insider/api/serializers.py
insider/api/urls.py
insider/api/views.py
insider/migrations/0001_initial.py
insider/migrations/0002_insidersetting.py
insider/migrations/0003_alter_insidersetting_value.py
insider/migrations/__init__.py
insider/services/__init__.py
insider/services/footprint.py
insider/services/jira.py
insider/services/slack.py
insider/static/insider/index.html
insider/static/insider/.vite/manifest.json
insider/static/insider/assets/index.css
insider/static/insider/assets/index.js
insider/tests/test_cleanup.py
insider/tests/test_db_routing.py
insider/tests/test_settings_safety.py
insider/tests/utils.py
django_insider-0.1.10.dist-info/METADATA
django_insider-0.1.10.dist-info/WHEEL
django_insider-0.1.10.dist-info/top_level.txt
django_insider-0.1.10.dist-info/RECORD
