Metadata-Version: 2.4
Name: django-insider
Version: 0.1.10
Summary: The missing observability dashboard for Django.
Author-email: Morakinyo Joseph <jmoraks03@gmail.com>
License-Expression: MIT
Project-URL: Homepage, https://github.com/Morakinyo-Joseph/django-insider
Project-URL: Repository, https://github.com/Morakinyo-Joseph/django-insider
Project-URL: Documentation, https://docs.google.com/document/d/1PnWshYnUwgQjzD5EDiG-HfkE37YIDSDdyvGJyhv2lM4/edit?tab=t.0
Keywords: django,middleware,monitoring,performance,celery,react
Classifier: Development Status :: 3 - Alpha
Classifier: Framework :: Django
Classifier: Framework :: Django :: 3.2
Classifier: Framework :: Django :: 4.0
Classifier: Framework :: Django :: 4.1
Classifier: Framework :: Django :: 4.2
Classifier: Framework :: Django :: 5.0
Classifier: Intended Audience :: Developers
Classifier: Operating System :: OS Independent
Classifier: Programming Language :: Python :: 3
Requires-Python: >=3.8
Requires-Dist: Django>=3.0
Requires-Dist: djangorestframework>=3.12
Requires-Dist: celery>=5.0
Requires-Dist: atlassian-python-api>=4.0
